lndgrpc/__init__.py
lndgrpc/__main__.py
lndgrpc/aio/__init__.py
lndgrpc/aio/async_client.py
lndgrpc/autopilot.py
lndgrpc/chainnotifier.py
lndgrpc/cli.py
lndgrpc/client.py
lndgrpc/common.py
lndgrpc/compiled/__init__.py
lndgrpc/compiled/autopilot.proto
lndgrpc/compiled/autopilot_pb2.py
lndgrpc/compiled/autopilot_pb2_grpc.py
lndgrpc/compiled/chainkit.proto
lndgrpc/compiled/chainkit_pb2.py
lndgrpc/compiled/chainkit_pb2_grpc.py
lndgrpc/compiled/chainnotifier.proto
lndgrpc/compiled/chainnotifier_pb2.py
lndgrpc/compiled/chainnotifier_pb2_grpc.py
lndgrpc/compiled/dev.proto
lndgrpc/compiled/dev_pb2.py
lndgrpc/compiled/dev_pb2_grpc.py
lndgrpc/compiled/invoices.proto
lndgrpc/compiled/invoices_pb2.py
lndgrpc/compiled/invoices_pb2_grpc.py
lndgrpc/compiled/lightning.proto
lndgrpc/compiled/lightning_pb2.py
lndgrpc/compiled/lightning_pb2_grpc.py
lndgrpc/compiled/lncli.proto
lndgrpc/compiled/lncli_pb2.py
lndgrpc/compiled/lncli_pb2_grpc.py
lndgrpc/compiled/neutrino.proto
lndgrpc/compiled/neutrino_pb2.py
lndgrpc/compiled/neutrino_pb2_grpc.py
lndgrpc/compiled/peers.proto
lndgrpc/compiled/peers_pb2.py
lndgrpc/compiled/peers_pb2_grpc.py
lndgrpc/compiled/router.proto
lndgrpc/compiled/router_pb2.py
lndgrpc/compiled/router_pb2_grpc.py
lndgrpc/compiled/signer.proto
lndgrpc/compiled/signer_pb2.py
lndgrpc/compiled/signer_pb2_grpc.py
lndgrpc/compiled/stateservice.proto
lndgrpc/compiled/stateservice_pb2.py
lndgrpc/compiled/stateservice_pb2_grpc.py
lndgrpc/compiled/verrpc.proto
lndgrpc/compiled/verrpc_pb2.py
lndgrpc/compiled/verrpc_pb2_grpc.py
lndgrpc/compiled/walletkit.proto
lndgrpc/compiled/walletkit_pb2.py
lndgrpc/compiled/walletkit_pb2_grpc.py
lndgrpc/compiled/walletunlocker.proto
lndgrpc/compiled/walletunlocker_pb2.py
lndgrpc/compiled/walletunlocker_pb2_grpc.py
lndgrpc/compiled/watchtower.proto
lndgrpc/compiled/watchtower_pb2.py
lndgrpc/compiled/watchtower_pb2_grpc.py
lndgrpc/compiled/wtclient.proto
lndgrpc/compiled/wtclient_pb2.py
lndgrpc/compiled/wtclient_pb2_grpc.py
lndgrpc/dev.py
fl21_lnd_grpc_client-0.6.0.dist-info/LICENSE
fl21_lnd_grpc_client-0.6.0.dist-info/METADATA
fl21_lnd_grpc_client-0.6.0.dist-info/WHEEL
fl21_lnd_grpc_client-0.6.0.dist-info/entry_points.txt
fl21_lnd_grpc_client-0.6.0.dist-info/RECORD
