Metadata-Version: 2.1
Name: fl21-lnd-grpc-client
Version: 0.6.0
Summary: feelancer21 edition: An rpc client for LND (lightning network deamon)
Home-page: https://github.com/feelancer21/lnd-grpc-client
License: MIT
Author: feelancer21
Author-email: test@email.com
Requires-Python: >=3.8.1,<4.0
Classifier: License :: OSI Approved :: MIT License
Classifier: Programming Language :: Python :: 3
Classifier: Programming Language :: Python :: 3.9
Classifier: Programming Language :: Python :: 3.10
Classifier: Programming Language :: Python :: 3.11
Requires-Dist: aiogrpc (>=1.8,<2.0)
Requires-Dist: click (>=8.1.3,<9.0.0)
Requires-Dist: googleapis-common-protos (>=1.53.0,<2.0.0)
Requires-Dist: grpcio (>=1.37.0,<2.0.0)
Requires-Dist: grpcio-tools (>=1.37.0,<2.0.0)
Requires-Dist: protobuf (>=3.15.8,<4.0.0)
Requires-Dist: protobuf3-to-dict (>=0.1.5,<0.2.0)
Requires-Dist: ptpython (>=3.0.20,<4.0.0)
Requires-Dist: yachalk (>=0.1.5,<0.2.0)
Project-URL: Repository, https://github.com/feelancer21/lnd-grpc-client
